Metadata-Version: 2.1
Name: sphindexer
Version: 0.12.1
Summary: A sphinx extension to replace the IndexEntries class.
Home-page: https://github.com/KaKkouo/sphindexer
Author: @koKekkoh
Maintainer: KaKkouo
License: BSD 2-Clause License
Download-URL: https://pypi.org/project/sphindexer/
Project-URL: Code, https://github.com/KaKkouo/sphindexer
Project-URL: Issue tracker, https://github.com/KaKkouo/sphindexer/issues
Keywords: sphinx,index,glossary,indexer,sphindexer
Platform: any
Classifier: Development Status :: 4 - Beta
Classifier: Framework :: Sphinx :: Extension
Classifier: Intended Audience :: Developers
Classifier: Intended Audience :: Education
Classifier: License :: OSI Approved :: BSD License
Classifier: Operating System :: OS Independent
Classifier: Programming Language :: Python :: 3.6
Classifier: Programming Language :: Python :: 3.7
Classifier: Programming Language :: Python :: 3.8
Classifier: Topic :: Documentation :: Sphinx
Classifier: Topic :: Text Processing :: Indexing
Classifier: Topic :: Utilities
License-File: LICENSE
